dearpygui_router/__init__.py
dearpygui_router/context.py
dearpygui_router/router.py
dearpygui_router/screen.py
dearpygui_router/stack.py
dearpygui_router/types.py
dearpygui_router/ui.py
dearpygui_router-0.1.0.dist-info/licenses/LICENSE
dearpygui_router-0.1.0.dist-info/METADATA
dearpygui_router-0.1.0.dist-info/WHEEL
dearpygui_router-0.1.0.dist-info/top_level.txt
dearpygui_router-0.1.0.dist-info/RECORD
