Metadata-Version: 2.4
Name: dearpygui-router
Version: 0.1.0
Summary: DearPyGui extension to make it easy to navigate between screens
Author-email: Gudjon Einar Magnusson <gudjon@notbadjon.com>
Classifier: Programming Language :: Python :: 3
Classifier: Programming Language :: Python :: 3.10
Classifier: Programming Language :: Python :: 3.11
Classifier: Programming Language :: Python :: 3.12
Classifier: Programming Language :: Python :: 3.13
Classifier: Programming Language :: Python :: 3 :: Only
Classifier: Intended Audience :: Developers
Classifier: License :: OSI Approved :: MIT License
Requires-Python: >=3.10
License-File: LICENSE
Requires-Dist: dearpygui>1.0.0
Dynamic: license-file
